{
  "first_prize_store_info": [
    {
      "name": "CN마트",
      "address": "울산 동구 대학길 42 1층",
      "store_id": "73160954",
      "type": ""
    }
  ],
  "second_prize_store_info": [
    {
      "name": "CN마트",
      "address": "울산 동구 대학길 42 1층",
      "store_id": "73160954",
      "type": ""
    },
    {
      "name": "CN마트",
      "address": "울산 동구 대학길 42 1층",
      "store_id": "73160954",
      "type": ""
    },
    {
      "name": "CN마트",
      "address": "울산 동구 대학길 42 1층",
      "store_id": "73160954",
      "type": ""
    },
    {
      "name": "CN마트",
      "address": "울산 동구 대학길 42 1층",
      "store_id": "73160954",
      "type": ""
    }
  ],
  "bonus_prize_store_info": [
    {
      "name": "대성복권",
      "address": "서울 동대문구 무학로 72 1층",
      "store_id": "71167559",
      "type": ""
    },
    {
      "name": "대성복권",
      "address": "서울 동대문구 무학로 72 1층",
      "store_id": "71167559",
      "type": ""
    },
    {
      "name": "대성복권",
      "address": "서울 동대문구 무학로 72 1층",
      "store_id": "71167559",
      "type": ""
    },
    {
      "name": "대성복권",
      "address": "서울 동대문구 무학로 72 1층",
      "store_id": "71167559",
      "type": ""
    },
    {
      "name": "대성복권",
      "address": "서울 동대문구 무학로 72 1층",
      "store_id": "71167559",
      "type": ""
    }
  ]
}