{
  "first_prize_store_info": [],
  "second_prize_store_info": [],
  "bonus_prize_store_info": [
    {
      "name": "복권방",
      "address": "대구광역시 서구 달서로 107 (비산동) 1층"
    },
    {
      "name": "복권방",
      "address": "대구광역시 서구 달서로 107 (비산동) 1층"
    },
    {
      "name": "복권방",
      "address": "대구광역시 서구 달서로 107 (비산동) 1층"
    },
    {
      "name": "복권방",
      "address": "대구광역시 서구 달서로 107 (비산동) 1층"
    },
    {
      "name": "복권방",
      "address": "대구광역시 서구 달서로 107 (비산동) 1층"
    }
  ]
}