{
  "first_prize_store_info": [
    {
      "name": "이마트24구미들성로점",
      "address": "경북 구미시 고아읍 들성로 106 (원호리) 1층"
    }
  ],
  "second_prize_store_info": [
    {
      "name": "이마트24구미들성로점",
      "address": "경북 구미시 고아읍 들성로 106 (원호리) 1층"
    },
    {
      "name": "이마트24구미들성로점",
      "address": "경북 구미시 고아읍 들성로 106 (원호리) 1층"
    },
    {
      "name": "이마트24구미들성로점",
      "address": "경북 구미시 고아읍 들성로 106 (원호리) 1층"
    },
    {
      "name": "이마트24구미들성로점",
      "address": "경북 구미시 고아읍 들성로 106 (원호리) 1층"
    },
    {
      "name": "인터넷 복권판매사이트",
      "address": "동행복권(dhlottery.co.kr)"
    }
  ],
  "bonus_prize_store_info": [
    {
      "name": "대박행진풍동점(복권판매점)",
      "address": "경기도 고양시 일산동구 숲속마을로 50-76 (풍동, 중앙프라자) 중앙프라자 1층"
    },
    {
      "name": "대박행진풍동점(복권판매점)",
      "address": "경기도 고양시 일산동구 숲속마을로 50-76 (풍동, 중앙프라자) 중앙프라자 1층"
    },
    {
      "name": "대박행진풍동점(복권판매점)",
      "address": "경기도 고양시 일산동구 숲속마을로 50-76 (풍동, 중앙프라자) 중앙프라자 1층"
    },
    {
      "name": "대박행진풍동점(복권판매점)",
      "address": "경기도 고양시 일산동구 숲속마을로 50-76 (풍동, 중앙프라자) 중앙프라자 1층"
    },
    {
      "name": "대박행진풍동점(복권판매점)",
      "address": "경기도 고양시 일산동구 숲속마을로 50-76 (풍동, 중앙프라자) 중앙프라자 1층"
    },
    {
      "name": "인터넷 복권판매사이트",
      "address": "동행복권(dhlottery.co.kr)"
    },
    {
      "name": "인터넷 복권판매사이트",
      "address": "동행복권(dhlottery.co.kr)"
    },
    {
      "name": "인터넷 복권판매사이트",
      "address": "동행복권(dhlottery.co.kr)"
    },
    {
      "name": "인터넷 복권판매사이트",
      "address": "동행복권(dhlottery.co.kr)"
    },
    {
      "name": "인터넷 복권판매사이트",
      "address": "동행복권(dhlottery.co.kr)"
    }
  ]
}