{
  "first_prize_store_info": [],
  "second_prize_store_info": [],
  "bonus_prize_store_info": [
    {
      "name": "광림마트",
      "address": "서울특별시 강남구  도곡로 213 (역삼동, 마고빌딩)  마고빌딩"
    },
    {
      "name": "광림마트",
      "address": "서울특별시 강남구  도곡로 213 (역삼동, 마고빌딩)  마고빌딩"
    },
    {
      "name": "광림마트",
      "address": "서울특별시 강남구  도곡로 213 (역삼동, 마고빌딩)  마고빌딩"
    },
    {
      "name": "광림마트",
      "address": "서울특별시 강남구  도곡로 213 (역삼동, 마고빌딩)  마고빌딩"
    },
    {
      "name": "광림마트",
      "address": "서울특별시 강남구  도곡로 213 (역삼동, 마고빌딩)  마고빌딩"
    },
    {
      "name": "인터넷 복권판매사이트",
      "address": "동행복권(dhlottery.co.kr)"
    }
  ]
}