{
  "first_prize_store_info": [
    {
      "name": "SE동해단봉점",
      "address": "강원도 동해시  강원남부로 4753-4 (단봉동) 1층"
    }
  ],
  "second_prize_store_info": [
    {
      "name": "SE동해단봉점",
      "address": "강원도 동해시  강원남부로 4753-4 (단봉동) 1층"
    },
    {
      "name": "SE동해단봉점",
      "address": "강원도 동해시  강원남부로 4753-4 (단봉동) 1층"
    },
    {
      "name": "SE동해단봉점",
      "address": "강원도 동해시  강원남부로 4753-4 (단봉동) 1층"
    },
    {
      "name": "SE동해단봉점",
      "address": "강원도 동해시  강원남부로 4753-4 (단봉동) 1층"
    }
  ],
  "bonus_prize_store_info": []
}