{
  "store_id": "11100495",
  "name": "또와식품",
  "address": "서울 강서구  양천로 694 ",
  "province": "서울",
  "city": "강서구",
  "phone": "02-3665-4377",
  "lottery_types": [
    "lotto645",
    "pension720",
    "speetto"
  ],
  "latitude": 37.550079,
  "longitude": 126.872827,
  "updated_at": "2026-02-03T18:24:13.343762",
  "first_prize_draws": [
    1096,
    566,
    445,
    437
  ],
  "second_prize_draws": [
    1137,
    1129,
    1076,
    1075,
    1059,
    1029,
    1002,
    944,
    902,
    823,
    804,
    755,
    692,
    657,
    402,
    313
  ],
  "first_prize_count": 4,
  "second_prize_count": 16
}