{
  "store_id": "11101122",
  "name": "가로판매점",
  "address": "서울 서대문구 신촌로 103 신촌역 3번4번출구 중앙 가로판매점  ",
  "province": "서울",
  "city": "서대문구",
  "phone": "02-392-6588",
  "lottery_types": [
    "lotto645",
    "pension720",
    "speetto"
  ],
  "latitude": 37.554991,
  "longitude": 126.93599,
  "updated_at": "2026-02-03T18:29:48.774987",
  "first_prize_draws": [
    1122,
    910,
    767,
    376
  ],
  "second_prize_draws": [
    1207,
    1093,
    1089,
    1058,
    1041,
    861,
    661,
    416
  ],
  "first_prize_count": 4,
  "second_prize_count": 8
}