{
  "store_id": "11100835",
  "name": "종로3가1호선역2번출구가로판매점82호",
  "address": "서울 종로구 돈화문로 23 가판  ",
  "phone": "02-743-6544",
  "lottery_types": [
    "lotto645",
    "pension720",
    "speetto"
  ],
  "latitude": 37.570703,
  "longitude": 126.991875,
  "updated_at": "2026-02-03T18:29:53.059720",
  "first_prize_draws": [
    1194,
    1153,
    1088,
    667,
    633,
    500,
    429
  ],
  "second_prize_draws": [
    1208,
    1189,
    1186,
    1175,
    1164,
    1151,
    1135,
    1134,
    1122,
    1111,
    1065,
    1057,
    1027,
    1022,
    1021,
    1019,
    995,
    990,
    985,
    984,
    965,
    933,
    926,
    912,
    881,
    832,
    799,
    774,
    755,
    707,
    666,
    640,
    591,
    552,
    545,
    508,
    495,
    493,
    464,
    453,
    360,
    308,
    281
  ],
  "first_prize_count": 7,
  "second_prize_count": 43
}