{
  "store_id": "11100644",
  "name": "우성슈퍼",
  "address": "서울 강동구  구천면로 371 ",
  "province": "서울",
  "city": "강동구",
  "phone": "02-427-6715",
  "lottery_types": [
    "lotto645",
    "pension720",
    "speetto"
  ],
  "latitude": 37.550729,
  "longitude": 127.139707,
  "updated_at": "2026-02-03T18:23:13.287610",
  "first_prize_draws": [
    893
  ],
  "second_prize_draws": [
    1123,
    1108,
    983,
    564
  ],
  "first_prize_count": 1,
  "second_prize_count": 4
}