{
  "store_id": "11101102",
  "name": "가로매점",
  "address": "서울 마포구  마포대로 61-1 ",
  "phone": "02-714-7863",
  "lottery_types": [
    "lotto645",
    "pension720",
    "speetto"
  ],
  "latitude": 37.541647,
  "longitude": 126.948014,
  "updated_at": "2026-02-03T18:23:43.449958",
  "first_prize_draws": [
    913
  ],
  "second_prize_draws": [
    1130,
    1107,
    1040,
    1031,
    866,
    692,
    604,
    538,
    494,
    490,
    464,
    321
  ],
  "first_prize_count": 1,
  "second_prize_count": 12
}