{
  "store_id": "12890051",
  "name": "갤럭시슈퍼",
  "address": "인천 남동구  남동대로921번길 1 ",
  "province": "인천",
  "city": "남동구",
  "phone": "032-433-5111",
  "lottery_types": [
    "lotto645",
    "pension720",
    "speetto"
  ],
  "latitude": 37.46459,
  "longitude": 126.707786,
  "updated_at": "2026-02-03T18:18:25.123333",
  "first_prize_draws": [],
  "second_prize_draws": [
    1063,
    869,
    803,
    781,
    741,
    718,
    692,
    599,
    528
  ],
  "first_prize_count": 0,
  "second_prize_count": 9
}