{
  "store_id": "14140154",
  "name": "1등복권방",
  "address": "경기 시흥시 은계번영길 7 112호  ",
  "province": "경기",
  "city": "시흥시",
  "phone": null,
  "lottery_types": [
    "lotto645",
    "pension720",
    "speetto"
  ],
  "latitude": 37.437098,
  "longitude": 126.80162,
  "updated_at": "2026-02-21T13:13:10.914962",
  "first_prize_draws": [
    913
  ],
  "second_prize_draws": [
    1212,
    1058,
    1020,
    1008,
    911,
    906,
    852,
    790
  ],
  "first_prize_count": 1,
  "second_prize_count": 8
}