{
  "store_id": "14140710",
  "name": "로또로또",
  "address": "경기 성남시 수정구  위례광장로 104 1층 1100호 (위례한화오벨리스크 센트럴스퀘어)",
  "province": "경기",
  "city": "성남시",
  "phone": null,
  "lottery_types": [
    "lotto645",
    "pension720",
    "speetto"
  ],
  "latitude": 37.473339,
  "longitude": 127.141012,
  "updated_at": "2026-02-03T18:19:54.345774",
  "first_prize_draws": [],
  "second_prize_draws": [
    1080,
    1067,
    1052
  ],
  "first_prize_count": 0,
  "second_prize_count": 3
}