{
  "store_id": "14210013",
  "name": "3억복권방",
  "address": "강원 태백시 황지동 30-8번지 ",
  "phone": "033-552-9805",
  "lottery_types": [
    "lotto645",
    "pension720",
    "speetto"
  ],
  "latitude": 37.169004,
  "longitude": 128.977785,
  "updated_at": "2026-02-03T18:03:27.160791",
  "first_prize_draws": [],
  "second_prize_draws": [
    881,
    776,
    729,
    718,
    675,
    611,
    595,
    575,
    553,
    493,
    476
  ],
  "first_prize_count": 0,
  "second_prize_count": 11
}