{
  "store_id": "14390021",
  "name": "두꺼비복권방",
  "address": "충북 청주시 서원구  산남로 47 104호",
  "province": "충북",
  "city": "청주시",
  "phone": "043-283-0044",
  "lottery_types": [
    "lotto645",
    "pension720",
    "speetto"
  ],
  "latitude": 36.610974,
  "longitude": 127.46878,
  "updated_at": "2026-02-03T18:27:12.000922",
  "first_prize_draws": [],
  "second_prize_draws": [
    1171,
    1145,
    857,
    836,
    746,
    536,
    492
  ],
  "first_prize_count": 0,
  "second_prize_count": 7
}