{
  "store_id": "14400075",
  "name": "정민책대여점",
  "address": "충남 천안시 서북구  서부16길 56 ",
  "province": "충남",
  "city": "천안시",
  "phone": null,
  "lottery_types": [
    "lotto645",
    "pension720",
    "speetto"
  ],
  "latitude": 36.821986,
  "longitude": 127.142598,
  "updated_at": "2026-02-03T18:26:28.447142",
  "first_prize_draws": [],
  "second_prize_draws": [
    1161,
    1057,
    831,
    595,
    557,
    468,
    325
  ],
  "first_prize_count": 0,
  "second_prize_count": 7
}