{
  "store_id": "14400050",
  "name": "대진복권방",
  "address": "충남 아산시 염치읍 서원리 27-8번지 ",
  "province": "충남",
  "city": "아산시",
  "phone": "041-533-1236",
  "lottery_types": [
    "lotto645",
    "speetto"
  ],
  "latitude": 36.839586,
  "longitude": 126.966733,
  "updated_at": "2026-02-03T17:55:55.030263",
  "first_prize_draws": [],
  "second_prize_draws": [
    786,
    777,
    723,
    716,
    562,
    559,
    496,
    415
  ],
  "first_prize_count": 0,
  "second_prize_count": 8
}