{
  "store_id": "14410112",
  "name": "로또명당해미점",
  "address": "충남 서산시  남문2로 108 ",
  "phone": "041-688-6004",
  "lottery_types": [
    "lotto645",
    "pension720",
    "speetto"
  ],
  "latitude": 36.71344,
  "longitude": 126.544188,
  "updated_at": "2026-02-03T18:27:07.204363",
  "first_prize_draws": [
    1170,
    1137,
    971,
    920,
    889,
    870,
    527
  ],
  "second_prize_draws": [
    1167,
    1166,
    1164,
    1160,
    1143,
    1137,
    1129,
    1126,
    1108,
    1094,
    1083,
    1079,
    1064,
    1021,
    1015,
    972,
    953,
    951,
    914,
    906,
    803,
    782,
    781,
    771,
    692,
    690,
    685,
    637,
    626,
    589,
    588,
    513,
    465,
    445,
    422,
    401,
    382,
    290
  ],
  "first_prize_count": 7,
  "second_prize_count": 38
}