{
  "store_id": "14420009",
  "name": "당진로또토토판매점",
  "address": "충남 당진시 당진중앙1로 129  ",
  "province": "충남",
  "city": "당진시",
  "phone": "041-352-0329",
  "lottery_types": [
    "lotto645",
    "pension720",
    "speetto"
  ],
  "latitude": 36.895459,
  "longitude": 126.6309,
  "updated_at": "2026-05-09T13:55:44.564159",
  "first_prize_draws": [
    793
  ],
  "second_prize_draws": [
    1223,
    1152,
    1093,
    1060,
    961,
    909,
    897,
    892,
    864,
    771,
    702
  ],
  "first_prize_count": 1,
  "second_prize_count": 11
}