{
  "draw_no": 387,
  "draw_date": "2010-05-01",
  "numbers": [
    1,
    26,
    31,
    34,
    40,
    43
  ],
  "bonus_number": 20,
  "prize_info": [
    {
      "rank": "1등",
      "total_prize": "10702134000",
      "winner_count": "4",
      "prize_per_winner": "2675533500"
    },
    {
      "rank": "2등",
      "total_prize": "1783689000",
      "winner_count": "26",
      "prize_per_winner": "68603424"
    },
    {
      "rank": "3등",
      "total_prize": "1783689000",
      "winner_count": "1177",
      "prize_per_winner": "1515454"
    },
    {
      "rank": "4등",
      "total_prize": "3567378000",
      "winner_count": "58115",
      "prize_per_winner": "61385"
    },
    {
      "rank": "5등",
      "total_prize": "4893090000",
      "winner_count": "978618",
      "prize_per_winner": "5000"
    }
  ],
  "total_sales_amount": "45459960000",
  "first_prize_store_info": [
    {
      "store_id": "11101524",
      "type": "자동"
    },
    {
      "store_id": "12900150",
      "type": "수동"
    },
    {
      "store_id": "14410030",
      "type": "자동"
    },
    {
      "store_id": "14910007",
      "type": "수동"
    }
  ],
  "second_prize_store_info": [
    {
      "store_id": "11101287",
      "type": null
    },
    {
      "store_id": "11101687",
      "type": null
    },
    {
      "store_id": "11110528",
      "type": null
    },
    {
      "store_id": "11110320",
      "type": null
    },
    {
      "store_id": "11101668",
      "type": null
    },
    {
      "store_id": "11100132",
      "type": null
    },
    {
      "store_id": "11110694",
      "type": null
    },
    {
      "store_id": "21100458",
      "type": null
    },
    {
      "store_id": "12700148",
      "type": null
    },
    {
      "store_id": "12710034",
      "type": null
    },
    {
      "store_id": "12910015",
      "type": null
    },
    {
      "store_id": "13000178",
      "type": null
    },
    {
      "store_id": "13100010",
      "type": null
    },
    {
      "store_id": "14100380",
      "type": null
    },
    {
      "store_id": "14110531",
      "type": null
    },
    {
      "store_id": "14100780",
      "type": null
    },
    {
      "store_id": "14100029",
      "type": null
    },
    {
      "store_id": "14210091",
      "type": null
    },
    {
      "store_id": "14210067",
      "type": null
    },
    {
      "store_id": "24200038",
      "type": null
    },
    {
      "store_id": "14690028",
      "type": null
    },
    {
      "store_id": "14690015",
      "type": null
    },
    {
      "store_id": "14600031",
      "type": null
    },
    {
      "store_id": "14700082",
      "type": null
    },
    {
      "store_id": "14810134",
      "type": null
    },
    {
      "store_id": "24800001",
      "type": null
    }
  ],
  "analysis_stats": {
    "number_properties": {
      "sum_total": 175,
      "odd_even_pattern": "3:3",
      "high_low_pattern": "1:5",
      "ac_value": 8,
      "prime_count": 2
    },
    "range_and_sequence": {
      "section_counts": {
        "unit": 1,
        "ten": 0,
        "twenty": 1,
        "thirty": 3,
        "forty": 1
      },
      "consecutive_sets": 0,
      "missing_sections": [
        "10"
      ]
    },
    "last_digit_stats": {
      "last_digit_sum": 15,
      "duplicate_last_digits": [
        1
      ]
    },
    "winner_insight": {
      "total_payout_rate": 50.0,
      "winner_method_rate": {
        "auto": 50.0,
        "manual": 50.0,
        "semi": 0.0
      },
      "tax_adjusted_prize": 1825607780
    }
  },
  "updated_at": "2026-03-05T23:17:54.862269"
}