{
  "draw_no": 79,
  "draw_date": "2004-06-05",
  "numbers": [
    3,
    12,
    24,
    27,
    30,
    32
  ],
  "bonus_number": 14,
  "prize_info": [
    {
      "rank": "1등",
      "total_prize": "0",
      "winner_count": "4",
      "prize_per_winner": "3416443800"
    },
    {
      "rank": "2등",
      "total_prize": "0",
      "winner_count": "31",
      "prize_per_winner": "73471910"
    },
    {
      "rank": "3등",
      "total_prize": "0",
      "winner_count": "1196",
      "prize_per_winner": "1904373"
    },
    {
      "rank": "4등",
      "total_prize": "0",
      "winner_count": "49431",
      "prize_per_winner": "92154"
    },
    {
      "rank": "5등",
      "total_prize": "0",
      "winner_count": "741871",
      "prize_per_winner": "10000"
    }
  ],
  "total_sales_amount": "60390004000",
  "first_prize_store_info": [],
  "updated_at": "2026-01-04T15:51:12.658430"
}