{
  "draw_no": 558,
  "draw_date": "2013-08-10",
  "numbers": [
    12,
    15,
    19,
    26,
    40,
    43
  ],
  "bonus_number": 29,
  "prize_info": [
    {
      "rank": "1등",
      "total_prize": "13159136625",
      "winner_count": "10",
      "prize_per_winner": "1315913663"
    },
    {
      "rank": "2등",
      "total_prize": "2193189438",
      "winner_count": "51",
      "prize_per_winner": "43003715"
    },
    {
      "rank": "3등",
      "total_prize": "2193189438",
      "winner_count": "1408",
      "prize_per_winner": "1557663"
    },
    {
      "rank": "4등",
      "total_prize": "3891700000",
      "winner_count": "77834",
      "prize_per_winner": "50000"
    },
    {
      "rank": "5등",
      "total_prize": "6032285000",
      "winner_count": "1206457",
      "prize_per_winner": "5000"
    }
  ],
  "total_sales_amount": "54939001000",
  "first_prize_store_info": [
    {
      "store_id": "11110236",
      "type": "수동"
    },
    {
      "store_id": "22800013",
      "type": "자동"
    },
    {
      "store_id": "14110334",
      "type": "자동"
    },
    {
      "store_id": "14110294",
      "type": "자동"
    },
    {
      "store_id": "14190134",
      "type": "자동"
    },
    {
      "store_id": "14110453",
      "type": "수동"
    },
    {
      "store_id": "14190100",
      "type": "자동"
    },
    {
      "store_id": "24100077",
      "type": "자동"
    },
    {
      "store_id": "14490014",
      "type": "자동"
    },
    {
      "store_id": "14610119",
      "type": "자동"
    }
  ],
  "second_prize_store_info": [
    {
      "store_id": "11110506",
      "type": null
    },
    {
      "store_id": "11101590",
      "type": null
    },
    {
      "store_id": "11101599",
      "type": null
    },
    {
      "store_id": "11100144",
      "type": null
    },
    {
      "store_id": "11110223",
      "type": null
    },
    {
      "store_id": "11190056",
      "type": null
    },
    {
      "store_id": "11101330",
      "type": null
    },
    {
      "store_id": "12690006",
      "type": null
    },
    {
      "store_id": "12600211",
      "type": null
    },
    {
      "store_id": "12610197",
      "type": null
    },
    {
      "store_id": "12600226",
      "type": null
    },
    {
      "store_id": "12600224",
      "type": null
    },
    {
      "store_id": "12600344",
      "type": null
    },
    {
      "store_id": "12600344",
      "type": null
    },
    {
      "store_id": "12710027",
      "type": null
    },
    {
      "store_id": "12790009",
      "type": null
    },
    {
      "store_id": "22700016",
      "type": null
    },
    {
      "store_id": "12800066",
      "type": null
    },
    {
      "store_id": "12990026",
      "type": null
    },
    {
      "store_id": "12910002",
      "type": null
    },
    {
      "store_id": "13110036",
      "type": null
    },
    {
      "store_id": "14100786",
      "type": null
    },
    {
      "store_id": "14100741",
      "type": null
    },
    {
      "store_id": "14190141",
      "type": null
    },
    {
      "store_id": "14110610",
      "type": null
    },
    {
      "store_id": "24100251",
      "type": null
    },
    {
      "store_id": "14110431",
      "type": null
    },
    {
      "store_id": "14100550",
      "type": null
    },
    {
      "store_id": "14100633",
      "type": null
    },
    {
      "store_id": "14100342",
      "type": null
    },
    {
      "store_id": "14110035",
      "type": null
    },
    {
      "store_id": "14100519",
      "type": null
    },
    {
      "store_id": "14110628",
      "type": null
    },
    {
      "store_id": "14100538",
      "type": null
    },
    {
      "store_id": "14100534",
      "type": null
    },
    {
      "store_id": "14390007",
      "type": null
    },
    {
      "store_id": "14300004",
      "type": null
    },
    {
      "store_id": "14300022",
      "type": null
    },
    {
      "store_id": "14310096",
      "type": null
    },
    {
      "store_id": "14410045",
      "type": null
    },
    {
      "store_id": "24400010",
      "type": null
    },
    {
      "store_id": "14510012",
      "type": null
    },
    {
      "store_id": "14710186",
      "type": null
    },
    {
      "store_id": "14710065",
      "type": null
    },
    {
      "store_id": "14700020",
      "type": null
    },
    {
      "store_id": "14890038",
      "type": null
    },
    {
      "store_id": "14800071",
      "type": null
    },
    {
      "store_id": "14890051",
      "type": null
    },
    {
      "store_id": "14800043",
      "type": null
    },
    {
      "store_id": "14810186",
      "type": null
    },
    {
      "store_id": "14810112",
      "type": null
    }
  ],
  "analysis_stats": {
    "number_properties": {
      "sum_total": 155,
      "odd_even_pattern": "3:3",
      "high_low_pattern": "3:3",
      "ac_value": 6,
      "prime_count": 2
    },
    "range_and_sequence": {
      "section_counts": {
        "unit": 0,
        "ten": 3,
        "twenty": 1,
        "thirty": 1,
        "forty": 1
      },
      "consecutive_sets": 0,
      "missing_sections": [
        "1"
      ]
    },
    "last_digit_stats": {
      "last_digit_sum": 25,
      "duplicate_last_digits": []
    },
    "winner_insight": {
      "total_payout_rate": 50.0,
      "winner_method_rate": {
        "auto": 80.0,
        "manual": 20.0,
        "semi": 0.0
      },
      "tax_adjusted_prize": 914662493
    }
  },
  "updated_at": "2026-03-05T23:27:56.584515"
}