{
  "draw_no": 171,
  "draw_date": "2006-03-11",
  "numbers": [
    4,
    16,
    25,
    29,
    34,
    35
  ],
  "bonus_number": 1,
  "prize_info": [
    {
      "rank": "1등",
      "total_prize": "11,768,038,200원",
      "winner_count": "6",
      "prize_per_winner": "1,961,339,700원"
    },
    {
      "rank": "2등",
      "total_prize": "1,961,339,714원",
      "winner_count": "19",
      "prize_per_winner": "103,228,406원"
    },
    {
      "rank": "3등",
      "total_prize": "1,961,340,392원",
      "winner_count": "1,381",
      "prize_per_winner": "1,420,232원"
    },
    {
      "rank": "4등",
      "total_prize": "3,922,708,673원",
      "winner_count": "71,461",
      "prize_per_winner": "54,893원"
    },
    {
      "rank": "5등",
      "total_prize": "5,565,340,000원",
      "winner_count": "1,113,068",
      "prize_per_winner": "5,000원"
    }
  ],
  "total_sales_amount": "50,357,474,000원",
  "first_prize_store_info": [],
  "updated_at": "2025-03-10T21:11:08.089498"
}