{
  "draw_no": 771,
  "draw_date": "2017-09-09",
  "numbers": [
    6,
    10,
    17,
    18,
    21,
    29
  ],
  "bonus_number": 30,
  "prize_info": [
    {
      "rank": "1등",
      "total_prize": "17450579628",
      "winner_count": "4",
      "prize_per_winner": "4362644907"
    },
    {
      "rank": "2등",
      "total_prize": "2908429986",
      "winner_count": "49",
      "prize_per_winner": "59355714"
    },
    {
      "rank": "3등",
      "total_prize": "2908431136",
      "winner_count": "2054",
      "prize_per_winner": "1415984"
    },
    {
      "rank": "4등",
      "total_prize": "5100650000",
      "winner_count": "102013",
      "prize_per_winner": "50000"
    },
    {
      "rank": "5등",
      "total_prize": "8404880000",
      "winner_count": "1680976",
      "prize_per_winner": "5000"
    }
  ],
  "total_sales_amount": "73545939000",
  "first_prize_store_info": [
    {
      "store_id": "11101663",
      "type": "수동"
    },
    {
      "store_id": "12900151",
      "type": "자동"
    },
    {
      "store_id": "12900103",
      "type": "자동"
    },
    {
      "store_id": "14190125",
      "type": "자동"
    }
  ],
  "second_prize_store_info": [
    {
      "store_id": "11110157",
      "type": null
    },
    {
      "store_id": "11101047",
      "type": null
    },
    {
      "store_id": "11190203",
      "type": null
    },
    {
      "store_id": "11101242",
      "type": null
    },
    {
      "store_id": "11190231",
      "type": null
    },
    {
      "store_id": "11190191",
      "type": null
    },
    {
      "store_id": "11190064",
      "type": null
    },
    {
      "store_id": "11110429",
      "type": null
    },
    {
      "store_id": "12600130",
      "type": null
    },
    {
      "store_id": "12610178",
      "type": null
    },
    {
      "store_id": "12620010",
      "type": null
    },
    {
      "store_id": "12600054",
      "type": null
    },
    {
      "store_id": "12600128",
      "type": null
    },
    {
      "store_id": "12620001",
      "type": null
    },
    {
      "store_id": "12790082",
      "type": null
    },
    {
      "store_id": "12790038",
      "type": null
    },
    {
      "store_id": "12700079",
      "type": null
    },
    {
      "store_id": "12890031",
      "type": null
    },
    {
      "store_id": "12840017",
      "type": null
    },
    {
      "store_id": "12830034",
      "type": null
    },
    {
      "store_id": "12940017",
      "type": null
    },
    {
      "store_id": "13000102",
      "type": null
    },
    {
      "store_id": "23020002",
      "type": null
    },
    {
      "store_id": "13100002",
      "type": null
    },
    {
      "store_id": "13110004",
      "type": null
    },
    {
      "store_id": "14140248",
      "type": null
    },
    {
      "store_id": "14130202",
      "type": null
    },
    {
      "store_id": "14110133",
      "type": null
    },
    {
      "store_id": "14110285",
      "type": null
    },
    {
      "store_id": "14100587",
      "type": null
    },
    {
      "store_id": "14100376",
      "type": null
    },
    {
      "store_id": "14110650",
      "type": null
    },
    {
      "store_id": "14140009",
      "type": null
    },
    {
      "store_id": "14110224",
      "type": null
    },
    {
      "store_id": "14100166",
      "type": null
    },
    {
      "store_id": "14100538",
      "type": null
    },
    {
      "store_id": "14320006",
      "type": null
    },
    {
      "store_id": "14390009",
      "type": null
    },
    {
      "store_id": "14410095",
      "type": null
    },
    {
      "store_id": "14410092",
      "type": null
    },
    {
      "store_id": "14410112",
      "type": null
    },
    {
      "store_id": "14420009",
      "type": null
    },
    {
      "store_id": "14700094",
      "type": null
    },
    {
      "store_id": "14700113",
      "type": null
    },
    {
      "store_id": "14800094",
      "type": null
    },
    {
      "store_id": "14830046",
      "type": null
    },
    {
      "store_id": "14810122",
      "type": null
    },
    {
      "store_id": "14910011",
      "type": null
    },
    {
      "store_id": "14900004",
      "type": null
    }
  ],
  "analysis_stats": {
    "number_properties": {
      "sum_total": 101,
      "odd_even_pattern": "3:3",
      "high_low_pattern": "5:1",
      "ac_value": 5,
      "prime_count": 2
    },
    "range_and_sequence": {
      "section_counts": {
        "unit": 2,
        "ten": 2,
        "twenty": 2,
        "thirty": 0,
        "forty": 0
      },
      "consecutive_sets": 1,
      "missing_sections": [
        "30",
        "40"
      ]
    },
    "last_digit_stats": {
      "last_digit_sum": 31,
      "duplicate_last_digits": []
    },
    "winner_insight": {
      "total_payout_rate": 50.0,
      "winner_method_rate": {
        "auto": 75.0,
        "manual": 25.0,
        "semi": 0.0
      },
      "tax_adjusted_prize": 2955972427
    }
  },
  "updated_at": "2026-03-05T23:37:48.711526"
}