{
  "draw_no": 1170,
  "draw_date": "2025-05-03",
  "numbers": [
    3,
    13,
    28,
    34,
    38,
    42
  ],
  "bonus_number": 25,
  "prize_info": [
    {
      "rank": "1등",
      "total_prize": "27731019380",
      "winner_count": "20",
      "prize_per_winner": "1386550969"
    },
    {
      "rank": "2등",
      "total_prize": "4621836600",
      "winner_count": "103",
      "prize_per_winner": "44872200"
    },
    {
      "rank": "3등",
      "total_prize": "4621840236",
      "winner_count": "5668",
      "prize_per_winner": "815427"
    },
    {
      "rank": "4등",
      "total_prize": "8193300000",
      "winner_count": "163866",
      "prize_per_winner": "50000"
    },
    {
      "rank": "5등",
      "total_prize": "13187005000",
      "winner_count": "2637401",
      "prize_per_winner": "5000"
    }
  ],
  "total_sales_amount": "116709995000",
  "first_prize_store_info": [
    {
      "store_id": "11100796",
      "type": "수동"
    },
    {
      "store_id": "11141044",
      "type": "수동"
    },
    {
      "store_id": "12740215",
      "type": "반자동"
    },
    {
      "store_id": "12700055",
      "type": "자동"
    },
    {
      "store_id": "12890025",
      "type": "자동"
    },
    {
      "store_id": "13140229",
      "type": "자동"
    },
    {
      "store_id": "14130222",
      "type": "수동"
    },
    {
      "store_id": "14142246",
      "type": "수동"
    },
    {
      "store_id": "14141448",
      "type": "자동"
    },
    {
      "store_id": "14100336",
      "type": "수동"
    },
    {
      "store_id": "14100505",
      "type": "자동"
    },
    {
      "store_id": "14140067",
      "type": "자동"
    },
    {
      "store_id": "14140352",
      "type": "자동"
    },
    {
      "store_id": "14240159",
      "type": "자동"
    },
    {
      "store_id": "14290012",
      "type": "자동"
    },
    {
      "store_id": "14410112",
      "type": "자동"
    },
    {
      "store_id": "14610087",
      "type": "수동"
    },
    {
      "store_id": "14700094",
      "type": "자동"
    },
    {
      "store_id": "14800180",
      "type": "수동"
    },
    {
      "store_id": "14840522",
      "type": "자동"
    }
  ],
  "second_prize_store_info": [
    {
      "store_id": "11100297",
      "type": null
    },
    {
      "store_id": "11100425",
      "type": null
    },
    {
      "store_id": "11140973",
      "type": null
    },
    {
      "store_id": "11100765",
      "type": null
    },
    {
      "store_id": "11100765",
      "type": null
    },
    {
      "store_id": "11100765",
      "type": null
    },
    {
      "store_id": "11141798",
      "type": null
    },
    {
      "store_id": "11141774",
      "type": null
    },
    {
      "store_id": "11101248",
      "type": null
    },
    {
      "store_id": "11190087",
      "type": null
    },
    {
      "store_id": "11141739",
      "type": null
    },
    {
      "store_id": "11101010",
      "type": null
    },
    {
      "store_id": "11110092",
      "type": null
    },
    {
      "store_id": "11110718",
      "type": null
    },
    {
      "store_id": "11110718",
      "type": null
    },
    {
      "store_id": "11140821",
      "type": null
    },
    {
      "store_id": "11101612",
      "type": null
    },
    {
      "store_id": "11141152",
      "type": null
    },
    {
      "store_id": "11140037",
      "type": null
    },
    {
      "store_id": "11100244",
      "type": null
    },
    {
      "store_id": "11140142",
      "type": null
    },
    {
      "store_id": "12600239",
      "type": null
    },
    {
      "store_id": "12600360",
      "type": null
    },
    {
      "store_id": "12600326",
      "type": null
    },
    {
      "store_id": "12640109",
      "type": null
    },
    {
      "store_id": "12700215",
      "type": null
    },
    {
      "store_id": "12710138",
      "type": null
    },
    {
      "store_id": "12710103",
      "type": null
    },
    {
      "store_id": "12790023",
      "type": null
    },
    {
      "store_id": "12840323",
      "type": null
    },
    {
      "store_id": "12800212",
      "type": null
    },
    {
      "store_id": "12800200",
      "type": null
    },
    {
      "store_id": "12840237",
      "type": null
    },
    {
      "store_id": "12800230",
      "type": null
    },
    {
      "store_id": "12840203",
      "type": null
    },
    {
      "store_id": "12840203",
      "type": null
    },
    {
      "store_id": "12840203",
      "type": null
    },
    {
      "store_id": "12990023",
      "type": null
    },
    {
      "store_id": "12900060",
      "type": null
    },
    {
      "store_id": "13000093",
      "type": null
    },
    {
      "store_id": "13040012",
      "type": null
    },
    {
      "store_id": "13090036",
      "type": null
    },
    {
      "store_id": "13090030",
      "type": null
    },
    {
      "store_id": "13100017",
      "type": null
    },
    {
      "store_id": "13140061",
      "type": null
    },
    {
      "store_id": "13100045",
      "type": null
    },
    {
      "store_id": "14141650",
      "type": null
    },
    {
      "store_id": "14142316",
      "type": null
    },
    {
      "store_id": "14140997",
      "type": null
    },
    {
      "store_id": "14120130",
      "type": null
    },
    {
      "store_id": "14142309",
      "type": null
    },
    {
      "store_id": "14141906",
      "type": null
    },
    {
      "store_id": "14100117",
      "type": null
    },
    {
      "store_id": "14110112",
      "type": null
    },
    {
      "store_id": "14190137",
      "type": null
    },
    {
      "store_id": "14100607",
      "type": null
    },
    {
      "store_id": "14100591",
      "type": null
    },
    {
      "store_id": "14142191",
      "type": null
    },
    {
      "store_id": "14140402",
      "type": null
    },
    {
      "store_id": "14100817",
      "type": null
    },
    {
      "store_id": "14140025",
      "type": null
    },
    {
      "store_id": "14100284",
      "type": null
    },
    {
      "store_id": "14190206",
      "type": null
    },
    {
      "store_id": "14142058",
      "type": null
    },
    {
      "store_id": "14140134",
      "type": null
    },
    {
      "store_id": "14100698",
      "type": null
    },
    {
      "store_id": "14141143",
      "type": null
    },
    {
      "store_id": "14190015",
      "type": null
    },
    {
      "store_id": "14141125",
      "type": null
    },
    {
      "store_id": "14140603",
      "type": null
    },
    {
      "store_id": "14100792",
      "type": null
    },
    {
      "store_id": "14140302",
      "type": null
    },
    {
      "store_id": "14290054",
      "type": null
    },
    {
      "store_id": "14290054",
      "type": null
    },
    {
      "store_id": "14240209",
      "type": null
    },
    {
      "store_id": "14210115",
      "type": null
    },
    {
      "store_id": "14240146",
      "type": null
    },
    {
      "store_id": "14200034",
      "type": null
    },
    {
      "store_id": "14290014",
      "type": null
    },
    {
      "store_id": "14300097",
      "type": null
    },
    {
      "store_id": "14330019",
      "type": null
    },
    {
      "store_id": "14340075",
      "type": null
    },
    {
      "store_id": "14310100",
      "type": null
    },
    {
      "store_id": "14340079",
      "type": null
    },
    {
      "store_id": "14310090",
      "type": null
    },
    {
      "store_id": "14410034",
      "type": null
    },
    {
      "store_id": "14440251",
      "type": null
    },
    {
      "store_id": "14540152",
      "type": null
    },
    {
      "store_id": "14540112",
      "type": null
    },
    {
      "store_id": "14590022",
      "type": null
    },
    {
      "store_id": "14500044",
      "type": null
    },
    {
      "store_id": "14610106",
      "type": null
    },
    {
      "store_id": "14620014",
      "type": null
    },
    {
      "store_id": "14740001",
      "type": null
    },
    {
      "store_id": "14730006",
      "type": null
    },
    {
      "store_id": "14790030",
      "type": null
    },
    {
      "store_id": "14700066",
      "type": null
    },
    {
      "store_id": "14840408",
      "type": null
    },
    {
      "store_id": "14840658",
      "type": null
    },
    {
      "store_id": "14890051",
      "type": null
    },
    {
      "store_id": "14840344",
      "type": null
    },
    {
      "store_id": "14840287",
      "type": null
    },
    {
      "store_id": "14940006",
      "type": null
    }
  ],
  "analysis_stats": {
    "number_properties": {
      "sum_total": 158,
      "odd_even_pattern": "2:4",
      "high_low_pattern": "2:4",
      "ac_value": 7,
      "prime_count": 2
    },
    "range_and_sequence": {
      "section_counts": {
        "unit": 1,
        "ten": 1,
        "twenty": 1,
        "thirty": 2,
        "forty": 1
      },
      "consecutive_sets": 0,
      "missing_sections": []
    },
    "last_digit_stats": {
      "last_digit_sum": 28,
      "duplicate_last_digits": [
        3,
        8
      ]
    },
    "winner_insight": {
      "total_payout_rate": 50.0,
      "winner_method_rate": {
        "auto": 60.0,
        "manual": 35.0,
        "semi": 5.0
      },
      "tax_adjusted_prize": 961989489
    }
  },
  "updated_at": "2026-03-05T23:59:11.961318"
}