{
  "draw_no": 1060,
  "draw_date": "2023-03-25",
  "numbers": [
    3,
    10,
    24,
    33,
    38,
    45
  ],
  "bonus_number": 36,
  "prize_info": [
    {
      "rank": "1등",
      "total_prize": "25150689396",
      "winner_count": "28",
      "prize_per_winner": "898238907"
    },
    {
      "rank": "2등",
      "total_prize": "4191781632",
      "winner_count": "96",
      "prize_per_winner": "43664392"
    },
    {
      "rank": "3등",
      "total_prize": "4191783078",
      "winner_count": "4593",
      "prize_per_winner": "912646"
    },
    {
      "rank": "4등",
      "total_prize": "8973750000",
      "winner_count": "179475",
      "prize_per_winner": "50000"
    },
    {
      "rank": "5등",
      "total_prize": "12830590000",
      "winner_count": "2566118",
      "prize_per_winner": "5000"
    }
  ],
  "total_sales_amount": "110677185000",
  "first_prize_store_info": [
    {
      "store_id": "11140678",
      "type": "수동"
    },
    {
      "store_id": "11100278",
      "type": "수동"
    },
    {
      "store_id": "11101432",
      "type": "수동"
    },
    {
      "store_id": "11130011",
      "type": "자동"
    },
    {
      "store_id": "11100250",
      "type": "자동"
    },
    {
      "store_id": "12690069",
      "type": "수동"
    },
    {
      "store_id": "12600094",
      "type": "자동"
    },
    {
      "store_id": "12600054",
      "type": "반자동"
    },
    {
      "store_id": "12600128",
      "type": "수동"
    },
    {
      "store_id": "12840088",
      "type": "수동"
    },
    {
      "store_id": "12810030",
      "type": "자동"
    },
    {
      "store_id": "12890004",
      "type": "자동"
    },
    {
      "store_id": "12800209",
      "type": "자동"
    },
    {
      "store_id": "13040120",
      "type": "자동"
    },
    {
      "store_id": "13190001",
      "type": "수동"
    },
    {
      "store_id": "14140509",
      "type": "자동"
    },
    {
      "store_id": "14110302",
      "type": "수동"
    },
    {
      "store_id": "14130169",
      "type": "수동"
    },
    {
      "store_id": "14110652",
      "type": "수동"
    },
    {
      "store_id": "14110086",
      "type": "수동"
    },
    {
      "store_id": "14440354",
      "type": "수동"
    },
    {
      "store_id": "14500030",
      "type": "자동"
    },
    {
      "store_id": "14540028",
      "type": "자동"
    },
    {
      "store_id": "14500103",
      "type": "자동"
    },
    {
      "store_id": "14710087",
      "type": "수동"
    },
    {
      "store_id": "14830016",
      "type": "자동"
    },
    {
      "store_id": "14800077",
      "type": "수동"
    },
    {
      "store_id": "14800031",
      "type": "수동"
    }
  ],
  "second_prize_store_info": [
    {
      "store_id": "11101687",
      "type": null
    },
    {
      "store_id": "11190121",
      "type": null
    },
    {
      "store_id": "11140965",
      "type": null
    },
    {
      "store_id": "11190001",
      "type": null
    },
    {
      "store_id": "11100176",
      "type": null
    },
    {
      "store_id": "11100952",
      "type": null
    },
    {
      "store_id": "51100000",
      "type": null
    },
    {
      "store_id": "11140310",
      "type": null
    },
    {
      "store_id": "11140889",
      "type": null
    },
    {
      "store_id": "11101127",
      "type": null
    },
    {
      "store_id": "11100263",
      "type": null
    },
    {
      "store_id": "12600130",
      "type": null
    },
    {
      "store_id": "12690037",
      "type": null
    },
    {
      "store_id": "12640475",
      "type": null
    },
    {
      "store_id": "12610018",
      "type": null
    },
    {
      "store_id": "12600097",
      "type": null
    },
    {
      "store_id": "12600122",
      "type": null
    },
    {
      "store_id": "12640160",
      "type": null
    },
    {
      "store_id": "12600054",
      "type": null
    },
    {
      "store_id": "12700119",
      "type": null
    },
    {
      "store_id": "12700311",
      "type": null
    },
    {
      "store_id": "12740097",
      "type": null
    },
    {
      "store_id": "12840194",
      "type": null
    },
    {
      "store_id": "12890054",
      "type": null
    },
    {
      "store_id": "12840050",
      "type": null
    },
    {
      "store_id": "12910002",
      "type": null
    },
    {
      "store_id": "12990006",
      "type": null
    },
    {
      "store_id": "13000068",
      "type": null
    },
    {
      "store_id": "13000068",
      "type": null
    },
    {
      "store_id": "13000175",
      "type": null
    },
    {
      "store_id": "13190018",
      "type": null
    },
    {
      "store_id": "13140123",
      "type": null
    },
    {
      "store_id": "13140070",
      "type": null
    },
    {
      "store_id": "13140056",
      "type": null
    },
    {
      "store_id": "14130197",
      "type": null
    },
    {
      "store_id": "14130197",
      "type": null
    },
    {
      "store_id": "14190168",
      "type": null
    },
    {
      "store_id": "14190240",
      "type": null
    },
    {
      "store_id": "14110553",
      "type": null
    },
    {
      "store_id": "14110146",
      "type": null
    },
    {
      "store_id": "14100741",
      "type": null
    },
    {
      "store_id": "14130155",
      "type": null
    },
    {
      "store_id": "14100753",
      "type": null
    },
    {
      "store_id": "14100365",
      "type": null
    },
    {
      "store_id": "14110542",
      "type": null
    },
    {
      "store_id": "14100582",
      "type": null
    },
    {
      "store_id": "14110609",
      "type": null
    },
    {
      "store_id": "14190117",
      "type": null
    },
    {
      "store_id": "14141375",
      "type": null
    },
    {
      "store_id": "14100498",
      "type": null
    },
    {
      "store_id": "14110053",
      "type": null
    },
    {
      "store_id": "14190020",
      "type": null
    },
    {
      "store_id": "14140136",
      "type": null
    },
    {
      "store_id": "14140363",
      "type": null
    },
    {
      "store_id": "14110187",
      "type": null
    },
    {
      "store_id": "14130211",
      "type": null
    },
    {
      "store_id": "14141685",
      "type": null
    },
    {
      "store_id": "14340081",
      "type": null
    },
    {
      "store_id": "14340081",
      "type": null
    },
    {
      "store_id": "14400013",
      "type": null
    },
    {
      "store_id": "14430050",
      "type": null
    },
    {
      "store_id": "14440283",
      "type": null
    },
    {
      "store_id": "14440292",
      "type": null
    },
    {
      "store_id": "14440360",
      "type": null
    },
    {
      "store_id": "14410015",
      "type": null
    },
    {
      "store_id": "14410015",
      "type": null
    },
    {
      "store_id": "14410015",
      "type": null
    },
    {
      "store_id": "14440020",
      "type": null
    },
    {
      "store_id": "14440245",
      "type": null
    },
    {
      "store_id": "14420009",
      "type": null
    },
    {
      "store_id": "14440130",
      "type": null
    },
    {
      "store_id": "14500150",
      "type": null
    },
    {
      "store_id": "14500034",
      "type": null
    },
    {
      "store_id": "14590055",
      "type": null
    },
    {
      "store_id": "14590055",
      "type": null
    },
    {
      "store_id": "14540038",
      "type": null
    },
    {
      "store_id": "14590013",
      "type": null
    },
    {
      "store_id": "14590011",
      "type": null
    },
    {
      "store_id": "14500018",
      "type": null
    },
    {
      "store_id": "14540038",
      "type": null
    },
    {
      "store_id": "14500112",
      "type": null
    },
    {
      "store_id": "14510128",
      "type": null
    },
    {
      "store_id": "14590009",
      "type": null
    },
    {
      "store_id": "14640138",
      "type": null
    },
    {
      "store_id": "14610019",
      "type": null
    },
    {
      "store_id": "14740230",
      "type": null
    },
    {
      "store_id": "14830019",
      "type": null
    },
    {
      "store_id": "14820029",
      "type": null
    },
    {
      "store_id": "14840205",
      "type": null
    },
    {
      "store_id": "14800025",
      "type": null
    },
    {
      "store_id": "14840450",
      "type": null
    },
    {
      "store_id": "14840427",
      "type": null
    },
    {
      "store_id": "14910012",
      "type": null
    },
    {
      "store_id": "14900002",
      "type": null
    },
    {
      "store_id": "14940044",
      "type": null
    },
    {
      "store_id": "14910009",
      "type": null
    }
  ],
  "analysis_stats": {
    "number_properties": {
      "sum_total": 153,
      "odd_even_pattern": "3:3",
      "high_low_pattern": "2:4",
      "ac_value": 6,
      "prime_count": 1
    },
    "range_and_sequence": {
      "section_counts": {
        "unit": 2,
        "ten": 0,
        "twenty": 1,
        "thirty": 2,
        "forty": 1
      },
      "consecutive_sets": 0,
      "missing_sections": [
        "10"
      ]
    },
    "last_digit_stats": {
      "last_digit_sum": 23,
      "duplicate_last_digits": [
        3
      ]
    },
    "winner_insight": {
      "total_payout_rate": 50.0,
      "winner_method_rate": {
        "auto": 42.9,
        "manual": 53.6,
        "semi": 3.6
      },
      "tax_adjusted_prize": 634820407
    }
  },
  "updated_at": "2026-03-05T23:53:25.716034"
}