{
  "draw_no": 1042,
  "draw_date": "2022-11-19",
  "numbers": [
    5,
    14,
    15,
    23,
    34,
    43
  ],
  "bonus_number": 4,
  "prize_info": [
    {
      "rank": "1등",
      "total_prize": "24,813,273,380원",
      "winner_count": "20",
      "prize_per_winner": "1,240,663,669원"
    },
    {
      "rank": "2등",
      "total_prize": "4,135,545,600원",
      "winner_count": "100",
      "prize_per_winner": "41,355,456원"
    },
    {
      "rank": "3등",
      "total_prize": "4,135,547,697원",
      "winner_count": "3,567",
      "prize_per_winner": "1,159,391원"
    },
    {
      "rank": "4등",
      "total_prize": "7,857,800,000원",
      "winner_count": "157,156",
      "prize_per_winner": "50,000원"
    },
    {
      "rank": "5등",
      "total_prize": "12,312,965,000원",
      "winner_count": "2,462,593",
      "prize_per_winner": "5,000원"
    }
  ],
  "total_sales_amount": "106,510,259,000원",
  "first_prize_store_info": [
    {
      "store_id": "11101169",
      "type": "수동"
    },
    {
      "store_id": "11110574",
      "type": "자동"
    },
    {
      "store_id": "11140117",
      "type": "수동"
    },
    {
      "store_id": "12690068",
      "type": "반자동"
    },
    {
      "store_id": "12840225",
      "type": "자동"
    },
    {
      "store_id": "12810040",
      "type": "자동"
    },
    {
      "store_id": "12820022",
      "type": "수동"
    },
    {
      "store_id": "14100793",
      "type": "자동"
    },
    {
      "store_id": "14130120",
      "type": "수동"
    },
    {
      "store_id": "14100195",
      "type": "자동"
    },
    {
      "store_id": "14210020",
      "type": "자동"
    },
    {
      "store_id": "14210089",
      "type": "자동"
    },
    {
      "store_id": "14600079",
      "type": "수동"
    },
    {
      "store_id": "14710130",
      "type": "수동"
    },
    {
      "store_id": "14710130",
      "type": "수동"
    },
    {
      "store_id": "14710130",
      "type": "수동"
    },
    {
      "store_id": "14710130",
      "type": "수동"
    },
    {
      "store_id": "14710130",
      "type": "수동"
    },
    {
      "store_id": "14710130",
      "type": "수동"
    },
    {
      "store_id": "14710130",
      "type": "수동"
    }
  ],
  "updated_at": "2025-03-10T23:19:14.333130"
}